coreftools/__init__.py
coreftools/corefresolvers.py
coreftools-1.1.1.dist-info/METADATA
coreftools-1.1.1.dist-info/WHEEL
coreftools-1.1.1.dist-info/top_level.txt
coreftools-1.1.1.dist-info/RECORD
