Metadata-Version: 2.1
Name: coreftools
Version: 1.1.1
Summary: Coreference-Resolution library
Author: Soumya-Ranjan-Sahoo
License: MIT
Requires-Dist: neuralcoref
Requires-Dist: spacy (==2.1.0)
Requires-Dist: allennlp
Requires-Dist: allennlp-models
Requires-Dist: pandas
Requires-Dist: openai
